bioscience/__init__.py
bioscience/_dependencies.py
bioscience/version.py
bioscience/base/__init__.py
bioscience/base/constants.py
bioscience/base/files.py
bioscience/base/models.py
bioscience/dataMining/__init__.py
bioscience/dataMining/biclustering/Bcca.py
bioscience/dataMining/biclustering/BiBit.py
bioscience/dataMining/biclustering/Biclustering.py
bioscience/dataMining/biclustering/__init__.py
bioscience/ensemble/EnsembleStats.py
bioscience/ensemble/__init__.py
bioscience/preprocess/Binarization.py
bioscience/preprocess/RnaSeq.py
bioscience/preprocess/Standard.py
bioscience/preprocess/__init__.py
bioscience/stats/__init__.py
bioscience/stats/correlation/__init__.py
bioscience/stats/correlation/continuous/DistCorr.py
bioscience/stats/correlation/continuous/Median.py
bioscience/stats/correlation/continuous/Pearson.py
bioscience/stats/correlation/continuous/Quadrant.py
bioscience/stats/correlation/continuous/__init__.py
bioscience/stats/correlation/dichotomic/Log_odds.py
bioscience/stats/correlation/dichotomic/MCC.py
bioscience/stats/correlation/dichotomic/PBC.py
bioscience/stats/correlation/dichotomic/__init__.py
bioscience/stats/correlation/mixed/ARI.py
bioscience/stats/correlation/mixed/CC.py
bioscience/stats/correlation/mixed/MI.py
bioscience/stats/correlation/mixed/NMI.py
bioscience/stats/correlation/mixed/__init__.py
bioscience/stats/correlation/ordinal/HoeffdingsD.py
bioscience/stats/correlation/ordinal/Kendall.py
bioscience/stats/correlation/ordinal/Spearman.py
bioscience/stats/correlation/ordinal/__init__.py
bioscience/stats/distance/Cosine.py
bioscience/stats/distance/Euclidean.py
bioscience/stats/distance/Jaccard.py
bioscience/stats/distance/Manhattan.py
bioscience/stats/distance/WeightedJaccard.py
bioscience/stats/distance/__init__.py
tests/__init__.py
bioscience-0.1.4.dist-info/LICENSE
bioscience-0.1.4.dist-info/METADATA
bioscience-0.1.4.dist-info/WHEEL
bioscience-0.1.4.dist-info/top_level.txt
bioscience-0.1.4.dist-info/RECORD
