Metadata-Version: 2.1
Name: bioscience
Version: 0.1.4
Summary: bioScience: A new Python science library for High-Performance Computing Bioinformatics Analytics
Home-page: https://github.com/aureliolfdez/bioscience
Download-URL: https://pypi.org/project/bioscience/#files
Maintainer: Aurelio Lopez-Fernandez
Maintainer-email: alopfer1@upo.es
License: BSD License
Project-URL: Bug Tracker, https://github.com/aureliolfdez/bioscience/issues
Project-URL: Documentation, https://bioscience.readthedocs.io/en/latest/
Project-URL: Source Code, https://github.com/aureliolfdez/bioscience
Keywords: python,data-science,data-mining,bioinformatics,high-performance-computing,data-analysis
Classifier: Programming Language :: Python :: 3
Classifier: Programming Language :: Python :: 3.11
Classifier: Programming Language :: Python :: 3.12
Classifier: License :: OSI Approved :: MIT License
Classifier: Operating System :: Microsoft :: Windows
Classifier: Operating System :: POSIX
Classifier: Operating System :: Unix
Classifier: Operating System :: MacOS
Classifier: Topic :: Scientific/Engineering
Classifier: Topic :: Software Development
Classifier: Intended Audience :: Science/Research
Classifier: Intended Audience :: Developers
Requires-Python: >=3.11
License-File: LICENSE
Requires-Dist: numpy>=2.0.1
Requires-Dist: pandas>=2.2.2
Requires-Dist: scikit-learn>=1.5.1
Requires-Dist: numba>=0.60.0
Requires-Dist: seaborn>=0.13.2
Requires-Dist: matplotlib>=3.9.0
Requires-Dist: setuptools>=75.1.0
Requires-Dist: requests>=2.32.3
